odoo/addons/mail_activity_cancel_tracking/README.rst
odoo/addons/mail_activity_cancel_tracking/__init__.py
odoo/addons/mail_activity_cancel_tracking/__manifest__.py
odoo/addons/mail_activity_cancel_tracking/data/mail_template_data.xml
odoo/addons/mail_activity_cancel_tracking/i18n/es.po
odoo/addons/mail_activity_cancel_tracking/i18n/it.po
odoo/addons/mail_activity_cancel_tracking/i18n/mail_activity_cancel_tracking.pot
odoo/addons/mail_activity_cancel_tracking/migrations/17.0.1.0.0/post-migration.py
odoo/addons/mail_activity_cancel_tracking/models/__init__.py
odoo/addons/mail_activity_cancel_tracking/models/mail_activity.py
odoo/addons/mail_activity_cancel_tracking/readme/CONTRIBUTORS.md
odoo/addons/mail_activity_cancel_tracking/readme/DESCRIPTION.md
odoo/addons/mail_activity_cancel_tracking/readme/USAGE.md
odoo/addons/mail_activity_cancel_tracking/static/description/icon.png
odoo/addons/mail_activity_cancel_tracking/static/description/index.html
odoo/addons/mail_activity_cancel_tracking/static/tests/tours/mail_activity_cancel_tracking.esm.js
odoo/addons/mail_activity_cancel_tracking/tests/__init__.py
odoo/addons/mail_activity_cancel_tracking/tests/test_mail_activity_cancel_tracking.py
odoo_addon_mail_activity_cancel_tracking-17.0.1.0.1.dist-info/METADATA
odoo_addon_mail_activity_cancel_tracking-17.0.1.0.1.dist-info/WHEEL
odoo_addon_mail_activity_cancel_tracking-17.0.1.0.1.dist-info/top_level.txt
odoo_addon_mail_activity_cancel_tracking-17.0.1.0.1.dist-info/RECORD
